[{"blockNum":900007,"timestamp":"2018-03-29T14:29:00","users":[{"name":"test-1","registrar":"1.2.7","id":"1.2.9783"}]},{"blockNum":900011,"timestamp":"2018-03-29T15:02:45","users":[{"name":"suzyuibe0225","registrar":"1.2.7","id":"1.2.9784"}]},{"blockNum":900022,"timestamp":"2018-03-29T15:49:06","users":[{"name":"scott53","registrar":"1.2.7","id":"1.2.9785"}]},{"blockNum":900029,"timestamp":"2018-03-29T17:18:57","users":[{"name":"skysonking88","registrar":"1.2.7","id":"1.2.9786"}]},{"blockNum":900034,"timestamp":"2018-03-30T00:49:51","users":[{"name":"oo9","registrar":"1.2.7","id":"1.2.9787"}]},{"blockNum":900050,"timestamp":"2018-03-30T03:17:09","users":[{"name":"zhp0260","registrar":"1.2.7","id":"1.2.9788"}]},{"blockNum":900056,"timestamp":"2018-03-30T03:27:54","users":[{"name":"yang-ye","registrar":"1.2.7","id":"1.2.9789"}]},{"blockNum":900060,"timestamp":"2018-03-30T03:51:12","users":[{"name":"chenguokun-1986","registrar":"1.2.7","id":"1.2.9790"}]},{"blockNum":900089,"timestamp":"2018-03-30T06:11:42","users":[{"name":"caesarchgk0310","registrar":"1.2.7","id":"1.2.9791"}]}]